{
  "document_name": "Anexos",
  "Publication Date": "",
  "regulation_type": "",
  "Law Identifier": "",
  "Law title": "Anexos",
  "url": "https://www.comunidad.madrid/sites/default/files/doc/educacion/instrucciones_de_28_de_julio_de_2009_anexos.pdf",
  "publication_ref": "",
  "Structural Elements": {
    "Preambulo": {
      "Content": "",
      "preambuloNumber": 0
    },
    "Titulo": [
      {
        "TitleNumber": 0,
        "TituloHeader": "",
        "content": "",
        "Capítulo": [
          {
            "CapítuloNumber": 0,
            "CapítuloHeader": "",
            "content": "",
            "Sección": [
              {
                "SecciónNumber": 0,
                "SecciónHeader": "",
                "content": "",
                "articles": [
                  {
                    "ArtículoNumber": 0,
                    "ArtículoHeader": "",
                    "content": "",
                    "subtitle": ""
                  }
                ]
              }
            ]
          }
        ]
      }
    ],
    "Disposición": [
      {
        "type": "",
        "DisposiciónHeader": "",
        "content": "",
        "subtitle": ""
      }
    ],
    "Anexo": {
      "Tablas": [
        {
          "TablaHeader": "",
          "content": ""
        }
      ],
      "structural_elements": [
        {
          "structural_elementtHeader": "ANEXO I\nDICTAMEN DE ESCOLARIZACIÓN",
          "rawContent": "DICTAMEN DE ESCOLARIZACIÓN\nDATOS PERSONALES\nAlumno/a:.............................................................................................................. NIA: ...........................................\nFecha de nacimiento:...................................................Edad.......................\nDomicilio.................................................................................................................Teléfono.......................\nEscolarizado en el centro (nombre/código) ...............................................................................Localidad............... Curso.......\n1.- CONCLUSIONES DEL PROCESO DE EVALUACIÓN PSICOPEDAGÓGICA\n1.- Desarrollo general. Nivel de competencia curricular. Otras condiciones significativas para el proceso de\nenseñanza y aprendizaje:\n2-:El/la alumno/a presenta necesidades educativas especiales asociadas a condiciones personales de\ndiscapacidad, previsiblemente permanentes, / trastorno de conducta por:\n1 .- Retraso mental (1)...................................................................................................................................................................................... \n2 .- Trastornos generalizados del desarrollo (2).............................................................................................................................................. \n3 .- Trastorno del desarrollo del lenguaje: de la expresión/de la comprensión .............................................................................................. \n4.- Trastornos del comportamiento y de las emociones de comienzo habitual en la infancia y en la adolescencia :Hiperactividad con\ndéficit de atención (2)................................................................................................................................................................................. \n5.- Trastornos del comportamiento y de las emociones de comienzo habitual en la infancia y en la adolescencia. Trastorno disocial (2) \n6 .- Pérdida o desviación significativa de la vista y funciones relacionadas (2) ............................................................................................ \n7 .- Pérdida o desviación significativa de las funciones auditivas y vestibulares (2)...................................................................................... \n8.- Pérdida o desviación significativa de las funciones neuromusculoesqueléticas y relacionadas con el movimiento (2)......................... \n9.- Plurideficiencias (retraso mental + otra).................................................................................................................................................... \n10.- Retraso madurativo (en la etapa de educación infantil)........................................................................................................................... \nInformación aportada por la familia\n Certificación de Minusvalía (indicar %)......................................................................................................................................................\n Diagnóstico Clínico .....................................................................................................................................................................................\n(1) Especificar el grado de retraso mental, a partir de primaria.\n(2) Aportar diagnóstico clínico en el momento que se disponga del mismo\n2.- ORIENTACIONES SOBRE LA PROPUESTA CURRICULAR\n1.-Características organizativas requeridas. Condiciones metodológicas relevantes. Indicaciones para la elaboración de\nlas adaptaciones del currículo.\n2.-Recursos materiales que se recomiendan.\n3.-Apoyos personales (especificar si precisa PT y/o AL)\nLos profesionales que han realizado la evaluación psicopedagógica\nEn Madrid, a.......... de ........................... de 200__\nFdo.:................................................. Fdo.:...............................................\n3.- PROPUESTA DE ESCOLARIZACIÓN\nConsiderando los datos de la evaluación psicopedagógica, reunido el Equipo o Departamento, (en su caso, el orientador\nde Centro de Educación Especial) se propone la escolarización del alumno/a en:\nCentro ordinario con atención educativa de apoyo \nCentro ordinario de escolarización preferente (*): Motórico  Auditivo  TGD \nCentro de Educación Especial \nPrograma de Cualificación Profesional Inicial \nEn el nivel: ........................................\nFecha prevista de revisión:..............................\n*Se adjuntará informe del EOEP Específico, si lo hubiere, correspondiente a la idoneidad de la propuesta\nVº Bº del Director/a o Jefe/a del Departamento de Orientación. Sello del Equipo/Centro.\n Fdo.:...............................................................\n4.- OPINIÓN DE LOS PADRES\nDon................................................................................................ y Doña.....................................................................\ncomo padres/tutores legales, del niño/a ………………………………………………………………NIA: ……………….\nMANIFIESTAN:\nQue han sido informados de que su hijo/a presenta:\n(Seleccionar la opción que proceda)\n1- Necesidades de acceso al currículo. Se propone escolarización en centro ordinario con los correspondientes\nrecursos materiales y/o personales\n2.- Necesidades educativas especiales asociadas a retraso madurativo, precisando modificaciones en el programa\neducativo de su grupo (sólo alumnado de educación infantil).\n3- Necesidades educativas especiales asociadas a discapacidad/trastorno de conducta, precisando modificaciones en\nel programa educativo de su grupo (adaptaciones curriculares significativas) así como apoyo especializado, durante\nparte del horario, que podrá realizarse fuera de su aula. Todo ello se reflejará en su historial académico.\nSe propone escolarización en Centro Ordinario con Apoyos\n4- Necesidades educativas especiales asociadas a discapacidad/trastorno de conducta, precisando distintos apoyos\nespecializados durante toda la jornada escolar, así como apoyos complementarios.\nSe propone escolarización en Centro Específico de Educación Especial.\nY que con respecto a la propuesta de escolarización están DE ACUERDO  EN DESACUERDO \nsolicitando plaza escolar en los siguientes centros, por orden de prioridad:\n1º............................................................................................ 4º............................................................................................\n2º............................................................................................ 5º............................................................................................\n3º............................................................................................ 6º............................................................................................\nObservaciones .............................................................................................................................................................................\n.....................................................................................................................................................................................................\n.....................................................................................................................................................................................................\nEn Madrid, a.......... de ........................... de 200....\n Firma del padre, madre o tutor legal ",
          "page": 1
        },
        {
          "structural_elementtHeader": "ANEXO II\nINFORME DEL SERVICIO DE INSPECCIÓN EDUCATIVA",
          "rawContent": "INFORME DEL SERVICIO DE INSPECCIÓN EDUCATIVA\nNombre y apellidos del alumno:.....................................................................................................................................NIA: ...................................\nDon/Doña............................................................................................................... Inspector/a de educación del Área Territorial\n.........................................., en relación con el dictamen de escolarización realizado por el Equipo de Orientación Educativa y\nPsicopedagógica....................................................... o el Departamento de Orientación............................................................ o el\ncolegio público de educación especial ……………………………….., conociendo la opinión de los padres y la información de\ndicho dictamen de escolarización.\nINFORMA :\nLa propuesta de escolarización formulada en el apartado 3 favorable  desfavorable \nLos centros educativos solicitados por los padres en el apartado 4 favorable  desfavorable  .\nObservaciones .............................................................................................................................................................................\n.....................................................................................................................................................................................................\n.....................................................................................................................................................................................................\nEn ................., a.......... de ........................... de 200....\n Vº Bº\nEl JEFE/A DEL SERVICIO DE INSPECCIÓN EDUCATIVA O JEFE/A DEL DISTRITO\n (Sello del Servicio de Inspección Educativa)\nEl INSPECTOR/A DE EDUCACIÓN\nFirmado......................................l Firmado..................................\n7\nINFORME DEL EQUIPO DE ORIENTACIÓN EDUCATIVA Y\nPSICOPEDAGÓGICA ESPECÍFICO\nNombre y apellidos del alumno ……………………………………………………………NIA: .…………….\nEl EOEP Específico de …………………………………………………………………………………………..\nEn base a las necesidades educativas especiales del alumno/a y las características de la respuesta\neducativa que requiere, considera adecuada la escolarización en:\nColegio Ordinario con Apoyos \nColegio de Escolarización Preferente \nCentro de Educación Especial \n En ................., a.......... de ........................... de 200....\nFdo.:.............................................. Fdo.:.............................................. Fdo.:..............................................\nVº Bº del Director/a del EOEP Específico\nFdo.: .......................................................................................",
          "page": 5
        }
      ]
    }
  }
}
